exorad/__init__.py
exorad/__version__.py
exorad/data/Zodi_map.hdf5
exorad/exorad.py
exorad/log/__init__.py
exorad/log/logger.py
exorad/models/__init__.py
exorad/models/foregrounds/__init__.py
exorad/models/foregrounds/skyForegrounds.py
exorad/models/foregrounds/zodiacalForeground.py
exorad/models/instruments/__init__.py
exorad/models/instruments/instrument.py
exorad/models/instruments/photometer.py
exorad/models/instruments/spectrometer.py
exorad/models/noise.py
exorad/models/optics/__init__.py
exorad/models/optics/opticalElement.py
exorad/models/optics/opticalPath.py
exorad/models/signal.py
exorad/models/source.py
exorad/models/target.py
exorad/models/targetlist.py
exorad/models/utils.py
exorad/output/__init__.py
exorad/output/hdf5/__init__.py
exorad/output/hdf5/hdf5.py
exorad/output/hdf5/util.py
exorad/output/output.py
exorad/tasks/__init__.py
exorad/tasks/foregroundHandler.py
exorad/tasks/instrumentHandler.py
exorad/tasks/loadOptions.py
exorad/tasks/loadSource.py
exorad/tasks/noiseHandler.py
exorad/tasks/propagateLight.py
exorad/tasks/targetHandler.py
exorad/tasks/task.py
exorad/utils/__init__.py
exorad/utils/ascii_art.py
exorad/utils/diffuse_light_propagation.py
exorad/utils/exolib.py
exorad/utils/mpi.py
exorad/utils/passVal.py
exorad/utils/plotter.py
exorad/utils/util.py
exorad/utils/version_control.py
exorad-2.1.127.dist-info/LICENSE
exorad-2.1.127.dist-info/METADATA
exorad-2.1.127.dist-info/WHEEL
exorad-2.1.127.dist-info/entry_points.txt
exorad-2.1.127.dist-info/RECORD
