Metadata-Version: 2.1
Name: exorad
Version: 2.1.127
Summary: The generic point source radiometric model
Home-page: https://github.com/ExObsSim/ExoRad2-public
License: BSD-3-Clause
Author: Lorenzo V. Mugnai
Author-email: lorenzo.mugnai@uniroma1.it
Requires-Python: >=3.9,<4.0
Classifier: Development Status :: 5 - Production/Stable
Classifier: Environment :: Console
Classifier: Intended Audience :: Developers
Classifier: Intended Audience :: Science/Research
Classifier: License :: OSI Approved :: BSD License
Classifier: Operating System :: OS Independent
Classifier: Operating System :: POSIX
Classifier: Operating System :: POSIX :: Linux
Classifier: Operating System :: Unix
Classifier: Programming Language :: Python :: 3
Classifier: Programming Language :: Python :: 3.9
Classifier: Programming Language :: Python :: 3.10
Classifier: Programming Language :: Python :: 3.11
Classifier: Programming Language :: Python :: 3.12
Classifier: Topic :: Scientific/Engineering
Classifier: Topic :: Software Development :: Libraries
Requires-Dist: astropy
Requires-Dist: h5py (>=3.2,<4.0)
Requires-Dist: matplotlib
Requires-Dist: mpmath
Requires-Dist: numpy
Requires-Dist: pandas
Requires-Dist: photutils
Requires-Dist: requests
Requires-Dist: scipy
Requires-Dist: xlrd (==1.2.0)
Requires-Dist: xlwt
Project-URL: Documentation, https://exorad2-public.readthedocs.io/en/latest/
Project-URL: Repository, https://github.com/ExObsSim/ExoRad2-public
